{
  "users": [
    {
      "id": "1",
      "name": "Alice"
    },
    {
      "id": "0a67",
      "name": "shuvo",
      "email": "shuvo@gmail.com",
      "age": 6,
      "gender": "M"
    },
    {
      "id": "fd24",
      "name": "Tushar",
      "email": "tushar@gmail.com",
      "age": 7,
      "gender": "M"
    },
    {
      "id": "119e",
      "name": "sohel",
      "email": "sohel@gmail.com",
      "age": 8,
      "gender": "M"
    },
    {
      "id": "31bf",
      "name": "tina",
      "email": "tina@gmail.com",
      "age": 3,
      "gender": "F"
    },
    {
      "name": "sohel bhai",
      "email": "sohel@gmail.com",
      "age": 7,
      "gender": "F",
      "id": "48dc"
    },
    {
      "id": "a382",
      "name": "Rongon",
      "email": "rongon@gmail.com",
      "age": 12,
      "gender": "M"
    },
    {
      "name": "Tanvir",
      "email": "tanvir@gmail.com",
      "age": 16,
      "gender": "M",
      "id": "f748"
    },
    {
      "name": "shuvo2",
      "email": "shuvo2@gmail.com",
      "age": 6,
      "gender": "M",
      "id": "c38e"
    }
  ]
}